dspy_ui/streamlit_app.py
dspy_ui-0.0.1rc1.dist-info/LICENSE
dspy_ui-0.0.1rc1.dist-info/WHEEL
dspy_ui-0.0.1rc1.dist-info/METADATA
dspy_ui-0.0.1rc1.dist-info/RECORD
